<?xml version = '1.0' encoding = 'UTF-8'?>
<Relation class="oracle.dbtools.crest.model.design.logical.Relation" name="Szczegoly_faktury" directorySegmentName="seg_0" id="AAD41E81-B3A1-EF09-BABD-1119C07ECF04">
<createdBy>s426287</createdBy>
<createdTime>2017-12-17 22:13:48 UTC</createdTime>
<ownerDesignName>dbForShop</ownerDesignName>
<engineerTo>
<item key="8F00BC8B-45A7-3EE3-19B2-788664E008C5" value="true"/>
<item key="F25F574C-561F-7EB8-94F7-10504D0039D3" value="true"/>
</engineerTo>
<sourcePk>2BA69137-C4B0-3CC5-5A1E-C19C3647439D</sourcePk>
<identifying>false</identifying>
<optionalSource>true</optionalSource>
<optionalTarget>false</optionalTarget>
<sourceCardinality>1</sourceCardinality>
<sourceEntity>0277C3F8-15B7-F018-5348-0DFCF971D93A</sourceEntity>
<targetCardinalityString>*</targetCardinalityString>
<targetEntity>210E77D2-D1D7-9E41-FB3C-7FF441E64DE2</targetEntity>
<transferable>true</transferable>
<deleteRule>NO ACTION</deleteRule>
</Relation>